jadio_llmnet/__init__.py
jadio_llmnet/cli/__init__.py
jadio_llmnet/cli/account.py
jadio_llmnet/cli/add.py
jadio_llmnet/cli/clicommands.json
jadio_llmnet/cli/init.py
jadio_llmnet/cli/login.py
jadio_llmnet/cli/logout.py
jadio_llmnet/cli/main.py
jadio_llmnet/cli/name.py
jadio_llmnet/cli/persist.py
jadio_llmnet/cli/remove.py
jadio_llmnet/cli/start.py
jadio_llmnet/cli/status.py
jadio_llmnet/cli/stop.py
jadio_llmnet/core/__init__.py
jadio_llmnet/core/encryptor.py
jadio_llmnet/core/exceptions.py
jadio_llmnet/core/hasher.py
jadio_llmnet/core/interpreter.py
jadio_llmnet/core/manager.py
jadio_llmnet/core/persistence.py
jadio_llmnet/core/server.py
jadio_llmnet/core/tray.py
jadio_llmnet-0.0.7.dist-info/METADATA
jadio_llmnet-0.0.7.dist-info/WHEEL
jadio_llmnet-0.0.7.dist-info/entry_points.txt
jadio_llmnet-0.0.7.dist-info/licenses/LICENSE
jadio_llmnet-0.0.7.dist-info/RECORD
