Metadata-Version: 2.4
Name: jadio-llmnet
Version: 0.0.7
Summary: Jadio-compatible extension package
License-Expression: MIT
License-File: LICENSE
Requires-Python: >=3.8
Requires-Dist: cryptography>=41.0.0
Requires-Dist: fastapi>=0.104.0
Requires-Dist: jadio>=0.0.2
Requires-Dist: pydantic>=2.0.0
Requires-Dist: uvicorn>=0.24.0
